[
  {
    "title": "R v. St-Onge Lamoureux, 2012 SCC 57 - DUI Case",
    "content": "CASE STUDY: R v. St-Onge Lamoureux, 2012 SCC 57\n\nFacts:\n- Mr. St-Onge Lamoureux was charged with impaired driving under Section 253 of the Criminal Code\n- He was stopped at a roadside check and required to provide a breath sample\n- He argued that the mandatory alcohol screening provisions violated his Charter rights\n\nLegal Issue:\n- Whether mandatory alcohol screening at roadside without reasonable suspicion violates Section 8 (unreasonable search) and Section 9 (arbitrary detention) of the Charter\n\nCourt Decision:\n- Supreme Court of Canada upheld the constitutionality of mandatory alcohol screening\n- Court found that the public interest in preventing impaired driving outweighed individual privacy interests\n- The minimal intrusion of a breath test was justified by the significant public safety concern\n\nSignificance:\n- Established that police can demand breath samples at roadside without reasonable suspicion\n- Confirmed that mandatory screening is a reasonable limit on Charter rights\n- Set precedent for DUI enforcement procedures across Canada\n\nCase Reference:\n- Citation: 2012 SCC 57\n- Court: Supreme Court of Canada\n- Date: October 19, 2012\n- Available at: CanLII (canlii.org)\n- Jurisdiction: Canada (Federal)\n\nCommon Questions:\n- Can police demand a breath test without suspicion in Canada?\n- What are your rights during a DUI stop in Canada?\n- Can you refuse a roadside breath test?\n- What is the difference between roadside screening and evidentiary breath test?",
    "jurisdiction": "Federal",
    "country": "Canada",
    "category": "case_study",
    "tags": [
      "dui",
      "charter",
      "supreme_court",
      "canada",
      "case_study"
    ],
    "case_reference": "2012 SCC 57",
    "court": "Supreme Court of Canada"
  },
  {
    "title": "Birchfield v. North Dakota, 579 U.S. ___ (2016) - DUI Case",
    "content": "CASE STUDY: Birchfield v. North Dakota, 579 U.S. ___ (2016)\n\nFacts:\n- Three separate cases consolidated: Birchfield, Bernard, and Beylund\n- All involved DUI arrests where drivers were required to submit to blood or breath tests\n- Drivers argued that warrantless blood and breath tests violated Fourth Amendment rights\n\nLegal Issue:\n- Whether warrantless breath tests and blood tests violate the Fourth Amendment prohibition on unreasonable searches\n\nCourt Decision:\n- Supreme Court held that warrantless breath tests are permissible as a search incident to arrest\n- However, warrantless blood tests require a warrant or exigent circumstances\n- Court distinguished between the minimal intrusion of breath tests vs. the more invasive blood tests\n\nSignificance:\n- Established that breath tests can be conducted without a warrant during DUI arrests\n- Blood tests require a warrant unless exigent circumstances exist\n- Set precedent for DUI enforcement procedures across the United States\n\nCase Reference:\n- Citation: 579 U.S. ___ (2016)\n- Court: Supreme Court of the United States\n- Date: June 23, 2016\n- Available at: Supreme Court website, Justia, Oyez\n- Jurisdiction: United States (Federal)\n\nCommon Questions:\n- Can police force a blood test without a warrant in the US?\n- What is the difference between breath and blood tests in DUI cases?\n- Can you refuse a breath test in the US?\n- What are exigent circumstances for warrantless blood tests?",
    "jurisdiction": "Federal",
    "country": "USA",
    "category": "case_study",
    "tags": [
      "dui",
      "fourth_amendment",
      "supreme_court",
      "usa",
      "case_study"
    ],
    "case_reference": "579 U.S. ___ (2016)",
    "court": "Supreme Court of the United States"
  },
  {
    "title": "R v. Grant, 2009 SCC 32 - Charter Rights Case",
    "content": "CASE STUDY: R v. Grant, 2009 SCC 32\n\nFacts:\n- Mr. Grant was charged with possession of a loaded firearm\n- Evidence was obtained after he was arbitrarily detained by police\n- He argued the evidence should be excluded under Section 24(2) of the Charter\n\nLegal Issue:\n- Whether evidence obtained in violation of Charter rights should be excluded\n- What test should be applied for exclusion of evidence under Section 24(2)\n\nCourt Decision:\n- Supreme Court established a new three-part test for exclusion of evidence:\n  1. Seriousness of the Charter-infringing state conduct\n  2. Impact on the Charter-protected interests of the accused\n  3. Society's interest in an adjudication on the merits\n- Court found the evidence should be excluded in this case\n\nSignificance:\n- Established the modern framework for exclusion of evidence in Canada\n- Replaced the old \"conscriptive evidence\" test\n- Provides guidance for courts on when to exclude improperly obtained evidence\n\nCase Reference:\n- Citation: 2009 SCC 32\n- Court: Supreme Court of Canada\n- Date: July 17, 2009\n- Available at: CanLII (canlii.org)\n- Jurisdiction: Canada (Federal)\n\nCommon Questions:\n- When can evidence be excluded in Canada?\n- What is the Grant test for exclusion of evidence?\n- Can illegally obtained evidence be used in court?\n- What are your rights if police violate the Charter?",
    "jurisdiction": "Federal",
    "country": "Canada",
    "category": "case_study",
    "tags": [
      "charter",
      "evidence",
      "supreme_court",
      "canada",
      "case_study"
    ],
    "case_reference": "2009 SCC 32",
    "court": "Supreme Court of Canada"
  },
  {
    "title": "Example Case: John Smith - DUI Arrest in Ontario",
    "content": "CASE STUDY EXAMPLE: John Smith - DUI Arrest in Ontario\n\nFacts:\n- Mr. John Smith was arrested on January 15, 2023, in Toronto, Ontario\n- He was stopped at a RIDE (Reduce Impaired Driving Everywhere) checkpoint\n- Breathalyzer test showed BAC of 0.12 (over the legal limit of 0.08)\n- Charged under Criminal Code Section 253(1)(b) - Operation While Over 80\n\nLegal Proceedings:\n- First appearance: February 1, 2023, at Old City Hall Courthouse, Toronto\n- Crown offered plea deal: Guilty plea to over 80, $1,500 fine, 1-year driving prohibition\n- Defense requested disclosure of breathalyzer calibration records\n- Trial date set for May 15, 2023\n\nOutcome:\n- Defense discovered breathalyzer was not properly calibrated\n- Crown withdrew charges due to insufficient evidence\n- Case dismissed on May 15, 2023\n\nLessons:\n- Importance of requesting full disclosure in DUI cases\n- Breathalyzer calibration records are critical evidence\n- Technical defenses can be successful in DUI cases\n- Always consult with a criminal defense lawyer\n\nCase Reference:\n- Court: Ontario Court of Justice, Old City Hall, Toronto\n- File Number: [Example format: 2023-ONCJ-001234]\n- Jurisdiction: Ontario, Canada\n- Similar cases available at: CanLII, Ontario Court decisions\n\nCommon Questions:\n- What should you do if charged with DUI in Ontario?\n- How do you request disclosure in a DUI case?\n- What are common defenses to DUI charges?\n- Can breathalyzer results be challenged?",
    "jurisdiction": "Ontario",
    "country": "Canada",
    "category": "case_study",
    "tags": [
      "dui",
      "ontario",
      "case_study",
      "example",
      "canada"
    ],
    "case_reference": "Example Case - Similar to real cases on CanLII",
    "court": "Ontario Court of Justice"
  }
]